cacimbao/__init__.py
cacimbao/datasets.py
cacimbao/helpers.py
cacimbao/loaders.py
cacimbao/data/aldeias-indigenas/aldeias-indigenas-08062025.parquet
cacimbao/data/aldeias-indigenas/datapackage.json
cacimbao/data/pescadores-e-pescadoras-profissionais/datapackage.json
cacimbao/data/pescadores-e-pescadoras-profissionais/pescadores-e-pescadoras-profissionais-07062025.parquet
cacimbao/data/pesquisa-nacional-de-saude-2019/datapackage.json
cacimbao/data/pesquisa-nacional-de-saude-2019/dicionario_PNS_microdados_2019_23062023.xls
cacimbao/data/salario-minimo-real-vigente/datapackage.json
cacimbao/data/salario-minimo-real-vigente/salario-minimo-real-vigente-04062025.parquet
cacimbao/data/sinpatinhas/datapackage.json
cacimbao/data/sinpatinhas/sinpatinhas-09122025.parquet
cacimbao-0.4.0.dist-info/METADATA
cacimbao-0.4.0.dist-info/WHEEL
cacimbao-0.4.0.dist-info/licenses/LICENSE
cacimbao-0.4.0.dist-info/RECORD
