Metadata-Version: 2.4
Name: cacimbao
Version: 0.4.0
Summary: Base de dados brasileiras com dados reais para propósitos educacionais
License-File: LICENSE
Requires-Python: >=3.12
Requires-Dist: narwhals>=0.7.0
Requires-Dist: polars>=0.20.0
Requires-Dist: requests>=2.31.0
